odoo9_addon_purchase_location_by_line-9.0.1.0.0-py2.7-nspkg.pth
odoo9_addon_purchase_location_by_line-9.0.1.0.0.dist-info/top_level.txt
odoo9_addon_purchase_location_by_line-9.0.1.0.0.dist-info/WHEEL
odoo9_addon_purchase_location_by_line-9.0.1.0.0.dist-info/RECORD
odoo9_addon_purchase_location_by_line-9.0.1.0.0.dist-info/metadata.json
odoo9_addon_purchase_location_by_line-9.0.1.0.0.dist-info/DESCRIPTION.rst
odoo9_addon_purchase_location_by_line-9.0.1.0.0.dist-info/METADATA
odoo9_addon_purchase_location_by_line-9.0.1.0.0.dist-info/namespace_packages.txt
odoo_addons/purchase_location_by_line/__openerp__.py
odoo_addons/purchase_location_by_line/__init__.py
odoo_addons/purchase_location_by_line/README.rst
odoo_addons/purchase_location_by_line/models/purchase.py
odoo_addons/purchase_location_by_line/models/__init__.py
odoo_addons/purchase_location_by_line/views/purchase_view.xml
odoo_addons/purchase_location_by_line/tests/__init__.py
odoo_addons/purchase_location_by_line/tests/test_purchase_delivery.py
odoo_addons/purchase_location_by_line/static/description/icon.png
